m3_object_coordination/__init__.py
m3_object_coordination/apps.py
m3_object_coordination/constants.py
m3_object_coordination/models.py
m3_object_coordination/signals.py
m3_object_coordination/utils.py
m3_object_coordination/_external_utils/__init__.py
m3_object_coordination/_external_utils/m3.py
m3_object_coordination/_external_utils/db/__init__.py
m3_object_coordination/_external_utils/db/models.py
m3_object_coordination/_external_utils/db/observer.py
m3_object_coordination/_external_utils/db/mixins/__init__.py
m3_object_coordination/_external_utils/db/mixins/date_interval.py
m3_object_coordination/_external_utils/db/mixins/validation.py
m3_object_coordination/_external_utils/utils/__init__.py
m3_object_coordination/_external_utils/utils/date.py
m3_object_coordination/_external_utils/utils/db.py
m3_object_coordination/_external_utils/utils/misc.py
m3_object_coordination/_external_utils/utils/system.py
m3_object_coordination/_external_utils/utils/ui.py
m3_object_coordination/_external_utils/utils/validation.py
m3_object_coordination/migrations/0001_initial.py
m3_object_coordination/migrations/__init__.py
m3_object_coordination/static/m3/js/ObjectCoordination.js
m3_object_coordination/ui/__init__.py
m3_object_coordination/ui/base/__init__.py
m3_object_coordination/ui/base/actions.py
m3_object_coordination/ui/base/approover-edit-window.js
m3_object_coordination/ui/base/components.py
m3_object_coordination/ui/routes/__init__.py
m3_object_coordination/ui/routes/actions.py
m3_object_coordination/ui/routes/components.py
m3_object_coordination/ui/routes/phase-edit-window.js
m3_object_coordination/ui/routes/review-window.js
m3_object_coordination/ui/routes/template-select-window.js
m3_object_coordination/ui/templates/__init__.py
m3_object_coordination/ui/templates/actions.py
m3_object_coordination/ui/templates/components.py
m3_object_coordination/ui/templates/list-window.js
m3_object_coordination/ui/templates/phase-edit-window.js
m3_object_coordination-1.1.0.dist-info/METADATA
m3_object_coordination-1.1.0.dist-info/WHEEL
m3_object_coordination-1.1.0.dist-info/dependency_links.txt
m3_object_coordination-1.1.0.dist-info/top_level.txt
m3_object_coordination-1.1.0.dist-info/RECORD
