Metadata-Version: 2.4
Name: m3-object-coordination
Version: 1.1.0
Summary: Подсистема для организации процессов согласования
Home-page: https://stash.bars-open.ru/projects/M3/repos/m3-object-coordination
Author: BARS Group
Author-email: education_dev@bars-open.ru
License: MIT
Classifier: Intended Audience :: Developers
Classifier: Environment :: Web Environment
Classifier: Natural Language :: Russian
Classifier: Operating System :: OS Independent
Classifier: Programming Language :: Python
Classifier: Programming Language :: Python :: 3.6
Classifier: Programming Language :: Python :: 3.7
Classifier: Development Status :: 5 - Production/Stable
Classifier: Framework :: Django :: 1.11
Classifier: Framework :: Django :: 2.0
Classifier: Framework :: Django :: 2.1
Classifier: Framework :: Django :: 2.2
Requires-Dist: python-dateutil<3,>=2
Requires-Dist: psycopg2-binary
Requires-Dist: django<3,>=1.11
Requires-Dist: m3-core<3,>=2.2
Requires-Dist: m3_django_compatibility<2,>=1.12.0
Requires-Dist: m3-ui<3,>=2.2.57
Requires-Dist: m3-objectpack<3,>=2.2
Dynamic: author
Dynamic: author-email
Dynamic: classifier
Dynamic: description
Dynamic: home-page
Dynamic: license
Dynamic: requires-dist
Dynamic: summary
